grangerthings/__init__.py
grangerthings/automata.py
grangerthings/predictor.py
grangerthings/quickhull.py
grangerthings/wordutils.py
grangerthings-0.0.6.dist-info/LICENSE.txt
grangerthings-0.0.6.dist-info/METADATA
grangerthings-0.0.6.dist-info/WHEEL
grangerthings-0.0.6.dist-info/top_level.txt
grangerthings-0.0.6.dist-info/RECORD
