Metadata-Version: 2.1
Name: grangerthings
Version: 0.0.6
Summary: Implementation of Granger networks
Author-email: Bas Testerink <btesterinkdev@gmail.com>
Classifier: Programming Language :: Python :: 3
Classifier: License :: OSI Approved :: MIT License
Classifier: Operating System :: OS Independent
Requires-Python: >=3.7
License-File: LICENSE.txt
